{"name":"Chickadee","comment":"If Urianger in bottom right, play bomb in bottom middle. If Hildibrand in top right, play bomb in top middle. Don\u0027t play Sylph in top right on 4th card played.","board":{"W":{"position":"W","card":{"name":"Godbert","abbrev":"god","player":"OTHER"},"turn":3},"E":{"position":"E","card":{"name":"Morbol","abbrev":"mor","player":"ME"},"turn":4},"C":{"position":"C","card":{"name":"Minfilia","abbrev":"min","player":"ME"},"turn":2},"SW":{"position":"SW","card":{"name":"Y\u0027shtola","abbrev":"ysh","player":"OTHER"},"turn":1}}}