{"name":"Vireo","comment":"If Elmer plays other than ¤ or ¥, keep baiting him around the board until turn 7 and play sylph. That should flip most of the board through Godbert \u003e Minfilia.","board":{"W":{"position":"W","card":{"name":"Godbert","abbrev":"god","player":"OTHER"},"turn":2},"C":{"position":"C","card":{"name":"Minfilia","abbrev":"min","player":"ME"},"turn":1},"N":{"position":"N","card":{"name":"Moogle","abbrev":"moo","player":"ME"},"turn":3},"NW":{"position":"NW","card":{"name":"Sylph","abbrev":"syl","player":"ME"},"turn":7}}}